arcane/__init__.py
arcane/hey.py
arcane_test2-0.0.2.dist-info/LICENSE.txt
arcane_test2-0.0.2.dist-info/METADATA
arcane_test2-0.0.2.dist-info/WHEEL
arcane_test2-0.0.2.dist-info/top_level.txt
arcane_test2-0.0.2.dist-info/RECORD
