Metadata-Version: 2.1
Name: arcane-test2
Version: 0.0.2
Summary: Say hello!
Home-page: UNKNOWN
Author: UNKNOWN
Author-email: UNKNOWN
License: UNKNOWN
Platform: UNKNOWN
